[
  {
    "Nation": "Mikeswill",
    "Junk Value": 16062.51,
    "Bank": 53854.11,
    "Deck Value": 2292151.24,
    "Card Count": 62883,
    "Deck Capacity": 31584,
    "Ultra-Rare": 3105,
    "Rare": 4636,
    "Common": 9806,
    "Uncommon": 30879,
    "Legendary": 13142,
    "Epic": 1315,
    "S1": 5580,
    "S2": 46669,
    "S3": 10634,
    "S1 Ultra-Rare": 107,
    "S1 Rare": 107,
    "S2 Common": 8080,
    "S1 Common": 1031,
    "S1 Uncommon": 2736,
    "S1 Legendary": 1460,
    "S2 Uncommon": 27903,
    "S2 Rare": 3609,
    "S1 Epic": 139,
    "S2 Ultra-Rare": 529,
    "S2 Legendary": 5944,
    "S2 Epic": 604,
    "S3 Ultra-Rare": 2469,
    "S3 Legendary": 5738,
    "S3 Epic": 572,
    "S3 Rare": 920,
    "S3 Common": 695,
    "S3 Uncommon": 240
  },
  {
    "Nation": "Koem Kab",
    "Junk Value": 26847.94,
    "Bank": 35553.89,
    "Deck Value": 1703083.9,
    "Card Count": 45155,
    "Deck Capacity": 22668,
    "Ultra-Rare": 1679,
    "Common": 7689,
    "Uncommon": 6395,
    "Epic": 3479,
    "Legendary": 24376,
    "Rare": 1537,
    "S1": 10112,
    "S2": 18618,
    "S3": 16425,
    "S1 Ultra-Rare": 475,
    "S1 Common": 2249,
    "S1 Uncommon": 1382,
    "S1 Epic": 830,
    "S2 Common": 4256,
    "S1 Legendary": 4678,
    "S1 Rare": 498,
    "S2 Ultra-Rare": 289,
    "S2 Uncommon": 4526,
    "S2 Legendary": 8654,
    "S2 Rare": 363,
    "S2 Epic": 530,
    "S3 Legendary": 11044,
    "S3 Rare": 676,
    "S3 Common": 1184,
    "S3 Epic": 2119,
    "S3 Ultra-Rare": 915,
    "S3 Uncommon": 487
  },
  {
    "Nation": "Giovanniland",
    "Junk Value": 1746.28,
    "Bank": 15164.12,
    "Deck Value": 757230.62,
    "Card Count": 67283,
    "Deck Capacity": 33668,
    "Uncommon": 8525,
    "Rare": 1848,
    "Common": 54593,
    "Ultra-Rare": 1558,
    "Legendary": 166,
    "Epic": 593,
    "S1": 2160,
    "S2": 16846,
    "S3": 48277,
    "S1 Uncommon": 671,
    "S1 Rare": 230,
    "S1 Common": 956,
    "S2 Common": 12130,
    "S2 Uncommon": 3026,
    "S2 Ultra-Rare": 875,
    "S1 Legendary": 8,
    "S1 Ultra-Rare": 209,
    "S1 Epic": 86,
    "S2 Rare": 417,
    "S2 Epic": 393,
    "S2 Legendary": 5,
    "S3 Uncommon": 4828,
    "S3 Common": 41507,
    "S3 Epic": 114,
    "S3 Rare": 1201,
    "S3 Ultra-Rare": 474,
    "S3 Legendary": 153
  },
  {
    "Nation": "Varanius",
    "Junk Value": 2903.24,
    "Bank": 5924.3,
    "Deck Value": 624613.68,
    "Card Count": 11460,
    "Deck Capacity": 5856,
    "Common": 4614,
    "Ultra-Rare": 1791,
    "Uncommon": 1698,
    "Rare": 758,
    "Legendary": 2229,
    "Epic": 370,
    "S1": 74,
    "S2": 1071,
    "S3": 10315,
    "S1 Common": 24,
    "S2 Common": 322,
    "S2 Ultra-Rare": 17,
    "S2 Uncommon": 499,
    "S2 Rare": 28,
    "S2 Legendary": 202,
    "S1 Uncommon": 35,
    "S2 Epic": 3,
    "S3 Rare": 726,
    "S3 Common": 4268,
    "S3 Uncommon": 1164,
    "S3 Ultra-Rare": 1771,
    "S3 Legendary": 2026,
    "S3 Epic": 360,
    "S1 Rare": 4,
    "S1 Ultra-Rare": 3,
    "S1 Epic": 7,
    "S1 Legendary": 1
  },
  {
    "Nation": "Noahs Second Country",
    "Junk Value": 9912.45,
    "Bank": 78829.19,
    "Deck Value": 599000.5,
    "Card Count": 10254,
    "Deck Capacity": 8037,
    "Common": 345,
    "Legendary": 9909,
    "S2": 345,
    "S3": 9909,
    "S2 Common": 345,
    "S3 Legendary": 9909
  },
  {
    "Nation": "Panagouge",
    "Junk Value": 529.29,
    "Bank": 5327.76,
    "Deck Value": 391499.72,
    "Card Count": 4706,
    "Deck Capacity": 2505,
    "Common": 2599,
    "Ultra-Rare": 202,
    "Rare": 219,
    "Uncommon": 1138,
    "Epic": 284,
    "Legendary": 264,
    "S1": 1382,
    "S2": 1470,
    "S3": 1854,
    "S1 Common": 1049,
    "S1 Ultra-Rare": 83,
    "S1 Rare": 75,
    "S1 Uncommon": 109,
    "S1 Epic": 52,
    "S1 Legendary": 14,
    "S2 Common": 704,
    "S2 Legendary": 189,
    "S2 Uncommon": 468,
    "S2 Ultra-Rare": 42,
    "S2 Epic": 25,
    "S2 Rare": 42,
    "S3 Uncommon": 561,
    "S3 Common": 846,
    "S3 Rare": 102,
    "S3 Legendary": 61,
    "S3 Epic": 207,
    "S3 Ultra-Rare": 77
  },
  {
    "Nation": "New Makasta",
    "Junk Value": 7811.07,
    "Bank": 3293.9,
    "Deck Value": 280722.74,
    "Card Count": 61845,
    "Deck Capacity": 31094,
    "Legendary": 3778,
    "Common": 30957,
    "Rare": 5290,
    "Ultra-Rare": 3117,
    "Uncommon": 13892,
    "Epic": 4811,
    "S1": 2406,
    "S2": 38607,
    "S3": 20832,
    "S1 Legendary": 82,
    "S1 Common": 743,
    "S1 Rare": 527,
    "S1 Ultra-Rare": 211,
    "S1 Uncommon": 709,
    "S1 Epic": 134,
    "S2 Uncommon": 9874,
    "S2 Rare": 3583,
    "S2 Epic": 1436,
    "S2 Common": 19939,
    "S2 Ultra-Rare": 2165,
    "S2 Legendary": 1610,
    "S3 Epic": 3241,
    "S3 Common": 10275,
    "S3 Ultra-Rare": 741,
    "S3 Legendary": 2086,
    "S3 Uncommon": 3309,
    "S3 Rare": 1180
  },
  {
    "Nation": "Seanat",
    "Junk Value": 5869.66,
    "Bank": 379.15,
    "Deck Value": 255927.11,
    "Card Count": 12049,
    "Deck Capacity": 6135,
    "Common": 2761,
    "Uncommon": 1781,
    "Rare": 931,
    "Legendary": 5104,
    "Ultra-Rare": 290,
    "Epic": 1182,
    "S1": 2246,
    "S2": 5154,
    "S3": 4649,
    "S1 Common": 578,
    "S1 Uncommon": 1151,
    "S1 Rare": 101,
    "S2 Legendary": 4315,
    "S1 Legendary": 261,
    "S1 Ultra-Rare": 79,
    "S1 Epic": 76,
    "S2 Ultra-Rare": 20,
    "S2 Epic": 181,
    "S2 Common": 391,
    "S2 Uncommon": 112,
    "S2 Rare": 135,
    "S3 Common": 1792,
    "S3 Uncommon": 518,
    "S3 Ultra-Rare": 191,
    "S3 Legendary": 528,
    "S3 Rare": 695,
    "S3 Epic": 925
  },
  {
    "Nation": "The Northern Light",
    "Junk Value": 3060.05,
    "Bank": 569.17,
    "Deck Value": 202435.14,
    "Card Count": 3075,
    "Deck Capacity": 15600,
    "Legendary": 3059,
    "Uncommon": 6,
    "Epic": 1,
    "Common": 5,
    "Rare": 3,
    "Ultra-Rare": 1,
    "S1": 853,
    "S2": 1496,
    "S3": 726,
    "S1 Legendary": 848,
    "S2 Legendary": 1490,
    "S2 Uncommon": 3,
    "S2 Epic": 1,
    "S1 Uncommon": 2,
    "S1 Common": 3,
    "S2 Common": 2,
    "S3 Legendary": 721,
    "S3 Rare": 3,
    "S3 Uncommon": 1,
    "S3 Ultra-Rare": 1
  },
  {
    "Nation": "Racoda",
    "Junk Value": 3979.05,
    "Bank": 904.99,
    "Deck Value": 200675.39,
    "Card Count": 31377,
    "Deck Capacity": 15834,
    "Common": 820,
    "Legendary": 2524,
    "Epic": 82,
    "Ultra-Rare": 68,
    "Uncommon": 27845,
    "Rare": 38,
    "S1": 562,
    "S2": 3201,
    "S3": 27614,
    "S1 Common": 62,
    "S1 Legendary": 220,
    "S2 Common": 715,
    "S1 Epic": 39,
    "S1 Ultra-Rare": 21,
    "S1 Uncommon": 205,
    "S2 Legendary": 2041,
    "S2 Ultra-Rare": 41,
    "S1 Rare": 15,
    "S2 Rare": 16,
    "S2 Uncommon": 356,
    "S2 Epic": 32,
    "S3 Uncommon": 27284,
    "S3 Legendary": 263,
    "S3 Common": 43,
    "S3 Rare": 7,
    "S3 Epic": 11,
    "S3 Ultra-Rare": 6
  },
  {
    "Nation": "The United Peoples Of Centrism",
    "Junk Value": 2779.38,
    "Bank": 5447.1,
    "Deck Value": 194025.41,
    "Card Count": 5878,
    "Deck Capacity": 6833,
    "Uncommon": 1301,
    "Common": 1383,
    "Legendary": 2540,
    "Rare": 219,
    "Ultra-Rare": 190,
    "Epic": 245,
    "S1": 681,
    "S2": 3653,
    "S3": 1544,
    "S1 Uncommon": 147,
    "S1 Common": 128,
    "S1 Legendary": 292,
    "S1 Rare": 40,
    "S2 Rare": 119,
    "S1 Ultra-Rare": 49,
    "S2 Ultra-Rare": 78,
    "S1 Epic": 25,
    "S2 Common": 542,
    "S2 Uncommon": 906,
    "S2 Legendary": 1966,
    "S2 Epic": 42,
    "S3 Common": 713,
    "S3 Epic": 178,
    "S3 Legendary": 282,
    "S3 Rare": 60,
    "S3 Uncommon": 248,
    "S3 Ultra-Rare": 63
  },
  {
    "Nation": "Upper Tuchoim",
    "Junk Value": 255.62,
    "Bank": 3371.44,
    "Deck Value": 191806.62,
    "Card Count": 5006,
    "Deck Capacity": 2644,
    "Rare": 642,
    "Common": 2897,
    "Uncommon": 655,
    "Ultra-Rare": 707,
    "Epic": 105,
    "S1": 176,
    "S2": 197,
    "S3": 4633,
    "S1 Rare": 16,
    "S1 Common": 131,
    "S2 Uncommon": 46,
    "S2 Common": 133,
    "S2 Rare": 12,
    "S2 Ultra-Rare": 5,
    "S2 Epic": 1,
    "S3 Common": 2633,
    "S3 Ultra-Rare": 700,
    "S3 Uncommon": 586,
    "S3 Rare": 614,
    "S1 Uncommon": 23,
    "S3 Epic": 100,
    "S1 Epic": 4,
    "S1 Ultra-Rare": 2
  },
  {
    "Nation": "Aerilia",
    "Junk Value": 2350.17,
    "Bank": 8224.99,
    "Deck Value": 161790.4,
    "Card Count": 4390,
    "Deck Capacity": 4931,
    "Common": 782,
    "Legendary": 2048,
    "Uncommon": 523,
    "Rare": 266,
    "Epic": 380,
    "Ultra-Rare": 391,
    "S1": 534,
    "S2": 1263,
    "S3": 2593,
    "S1 Common": 166,
    "S1 Legendary": 242,
    "S1 Uncommon": 65,
    "S1 Rare": 15,
    "S1 Epic": 21,
    "S2 Uncommon": 142,
    "S2 Ultra-Rare": 118,
    "S2 Rare": 50,
    "S1 Ultra-Rare": 25,
    "S2 Epic": 98,
    "S2 Legendary": 610,
    "S2 Common": 245,
    "S3 Rare": 201,
    "S3 Uncommon": 316,
    "S3 Ultra-Rare": 248,
    "S3 Common": 371,
    "S3 Epic": 261,
    "S3 Legendary": 1196
  },
  {
    "Nation": "Fhaengshia",
    "Junk Value": 2669.24,
    "Bank": 1309.36,
    "Deck Value": 157515.58,
    "Card Count": 4467,
    "Deck Capacity": 6833,
    "Rare": 489,
    "Legendary": 2320,
    "Ultra-Rare": 616,
    "Epic": 410,
    "Uncommon": 368,
    "Common": 264,
    "S1": 401,
    "S2": 2430,
    "S3": 1636,
    "S1 Rare": 25,
    "S1 Legendary": 200,
    "S2 Legendary": 1814,
    "S1 Ultra-Rare": 66,
    "S1 Epic": 66,
    "S1 Uncommon": 24,
    "S1 Common": 20,
    "S2 Ultra-Rare": 208,
    "S2 Uncommon": 83,
    "S2 Epic": 86,
    "S2 Common": 215,
    "S2 Rare": 24,
    "S3 Uncommon": 261,
    "S3 Rare": 440,
    "S3 Ultra-Rare": 342,
    "S3 Epic": 258,
    "S3 Legendary": 306,
    "S3 Common": 29
  },
  {
    "Nation": "Witchcraft And Sorcery",
    "Junk Value": 2499.26,
    "Bank": 855.29,
    "Deck Value": 155292.39,
    "Card Count": 11549,
    "Deck Capacity": 5893,
    "Legendary": 2129,
    "Rare": 281,
    "Uncommon": 385,
    "Common": 7931,
    "Epic": 357,
    "Ultra-Rare": 466,
    "S1": 599,
    "S2": 1533,
    "S3": 9417,
    "S1 Legendary": 232,
    "S1 Rare": 26,
    "S1 Uncommon": 54,
    "S2 Common": 374,
    "S1 Common": 217,
    "S1 Epic": 51,
    "S2 Legendary": 714,
    "S1 Ultra-Rare": 19,
    "S2 Epic": 131,
    "S2 Rare": 158,
    "S2 Ultra-Rare": 91,
    "S2 Uncommon": 65,
    "S3 Legendary": 1183,
    "S3 Ultra-Rare": 356,
    "S3 Common": 7340,
    "S3 Uncommon": 266,
    "S3 Epic": 175,
    "S3 Rare": 97
  },
  {
    "Nation": "Frisbeeteria",
    "Junk Value": 20458.65,
    "Bank": 42521.88,
    "Deck Value": 153950.27,
    "Card Count": 40093,
    "Deck Capacity": 20279,
    "Epic": 37426,
    "Legendary": 1729,
    "Common": 805,
    "Uncommon": 104,
    "Ultra-Rare": 17,
    "Rare": 12,
    "S1": 8122,
    "S2": 15107,
    "S3": 16864,
    "S1 Epic": 6419,
    "S1 Legendary": 1291,
    "S2 Epic": 14196,
    "S1 Common": 322,
    "S1 Uncommon": 80,
    "S2 Legendary": 387,
    "S1 Ultra-Rare": 9,
    "S2 Common": 482,
    "S1 Rare": 1,
    "S2 Rare": 11,
    "S2 Uncommon": 24,
    "S2 Ultra-Rare": 7,
    "S3 Epic": 16811,
    "S3 Legendary": 51,
    "S3 Ultra-Rare": 1,
    "S3 Common": 1
  },
  {
    "Nation": "Kwaj",
    "Junk Value": 1979.26,
    "Bank": 4509.82,
    "Deck Value": 143088.15,
    "Card Count": 4091,
    "Deck Capacity": 5393,
    "Epic": 831,
    "Legendary": 1517,
    "Common": 1321,
    "Ultra-Rare": 114,
    "Uncommon": 215,
    "Rare": 93,
    "S1": 1299,
    "S2": 823,
    "S3": 1969,
    "S1 Epic": 171,
    "S1 Legendary": 487,
    "S1 Common": 548,
    "S1 Ultra-Rare": 15,
    "S1 Uncommon": 66,
    "S1 Rare": 12,
    "S2 Legendary": 238,
    "S2 Epic": 290,
    "S2 Common": 261,
    "S2 Uncommon": 23,
    "S2 Ultra-Rare": 8,
    "S2 Rare": 3,
    "S3 Legendary": 792,
    "S3 Common": 512,
    "S3 Epic": 370,
    "S3 Rare": 78,
    "S3 Ultra-Rare": 91,
    "S3 Uncommon": 126
  },
  {
    "Nation": "Vulxo",
    "Junk Value": 1114.16,
    "Bank": 144.67,
    "Deck Value": 140950.68,
    "Card Count": 2833,
    "Deck Capacity": 1668,
    "Common": 1306,
    "Epic": 112,
    "Uncommon": 170,
    "Legendary": 1034,
    "Rare": 198,
    "Ultra-Rare": 13,
    "S1": 119,
    "S2": 132,
    "S3": 2582,
    "S1 Common": 87,
    "S1 Epic": 24,
    "S1 Uncommon": 6,
    "S2 Legendary": 67,
    "S2 Common": 62,
    "S1 Legendary": 2,
    "S2 Uncommon": 3,
    "S3 Common": 1157,
    "S3 Rare": 198,
    "S3 Uncommon": 161,
    "S3 Legendary": 965,
    "S3 Epic": 88,
    "S3 Ultra-Rare": 13
  },
  {
    "Nation": "Kractero",
    "Junk Value": 1891.94,
    "Bank": 8819.16,
    "Deck Value": 139899.45,
    "Card Count": 4391,
    "Deck Capacity": 2255,
    "Common": 2059,
    "Ultra-Rare": 77,
    "Epic": 132,
    "Legendary": 1775,
    "Uncommon": 299,
    "Rare": 49,
    "S1": 2071,
    "S2": 3,
    "S3": 2317,
    "S1 Common": 1545,
    "S1 Ultra-Rare": 74,
    "S1 Epic": 58,
    "S1 Legendary": 95,
    "S1 Uncommon": 279,
    "S1 Rare": 20,
    "S2 Epic": 1,
    "S3 Legendary": 1678,
    "S3 Common": 514,
    "S3 Epic": 73,
    "S3 Uncommon": 20,
    "S3 Rare": 29,
    "S2 Legendary": 2,
    "S3 Ultra-Rare": 3
  },
  {
    "Nation": "Feu De Glace",
    "Junk Value": 1041.98,
    "Bank": 13223.07,
    "Deck Value": 138535.58,
    "Card Count": 1573,
    "Deck Capacity": 4479,
    "Legendary": 961,
    "Uncommon": 59,
    "Ultra-Rare": 128,
    "Common": 293,
    "Epic": 99,
    "Rare": 33,
    "S2": 640,
    "S1": 660,
    "S3": 273,
    "S2 Legendary": 434,
    "S1 Uncommon": 37,
    "S1 Ultra-Rare": 104,
    "S1 Common": 119,
    "S1 Epic": 82,
    "S1 Legendary": 297,
    "S1 Rare": 21,
    "S2 Rare": 9,
    "S2 Ultra-Rare": 21,
    "S2 Common": 143,
    "S2 Epic": 14,
    "S2 Uncommon": 19,
    "S3 Epic": 3,
    "S3 Legendary": 230,
    "S3 Uncommon": 3,
    "S3 Common": 31,
    "S3 Ultra-Rare": 3,
    "S3 Rare": 3
  },
  {
    "Nation": "National Park Service",
    "Junk Value": 1936.28,
    "Bank": 8101.95,
    "Deck Value": 126161.16,
    "Card Count": 3316,
    "Deck Capacity": 5000,
    "Uncommon": 217,
    "Legendary": 1782,
    "Common": 693,
    "Ultra-Rare": 205,
    "Epic": 191,
    "Rare": 228,
    "S2": 84,
    "S3": 3186,
    "S1": 46,
    "S2 Uncommon": 65,
    "S3 Legendary": 1766,
    "S3 Common": 670,
    "S2 Common": 6,
    "S3 Uncommon": 140,
    "S3 Ultra-Rare": 201,
    "S3 Epic": 186,
    "S3 Rare": 223,
    "S1 Epic": 4,
    "S1 Common": 17,
    "S1 Rare": 2,
    "S1 Legendary": 9,
    "S1 Uncommon": 12,
    "S2 Legendary": 7,
    "S2 Epic": 1,
    "S2 Ultra-Rare": 2,
    "S1 Ultra-Rare": 2,
    "S2 Rare": 3
  },
  {
    "Nation": "Thorn1000",
    "Junk Value": 2031.94,
    "Bank": 4409.45,
    "Deck Value": 122038.8,
    "Card Count": 3212,
    "Deck Capacity": 1796,
    "Common": 674,
    "Epic": 141,
    "Legendary": 1929,
    "Rare": 209,
    "Uncommon": 174,
    "Ultra-Rare": 85,
    "S1": 56,
    "S2": 239,
    "S3": 2917,
    "S1 Common": 24,
    "S1 Epic": 3,
    "S2 Legendary": 170,
    "S2 Common": 43,
    "S2 Epic": 5,
    "S2 Rare": 5,
    "S2 Uncommon": 14,
    "S1 Legendary": 3,
    "S1 Uncommon": 23,
    "S1 Rare": 3,
    "S2 Ultra-Rare": 2,
    "S3 Uncommon": 137,
    "S3 Legendary": 1756,
    "S3 Ultra-Rare": 83,
    "S3 Rare": 201,
    "S3 Common": 607,
    "S3 Epic": 133
  },
  {
    "Nation": "Portsville",
    "Junk Value": 2169.81,
    "Bank": 2545.59,
    "Deck Value": 118393.14,
    "Card Count": 3025,
    "Deck Capacity": 3279,
    "Legendary": 2016,
    "Uncommon": 125,
    "Ultra-Rare": 470,
    "Common": 256,
    "Epic": 102,
    "Rare": 56,
    "S1": 228,
    "S2": 923,
    "S3": 1874,
    "S1 Legendary": 88,
    "S1 Uncommon": 61,
    "S2 Legendary": 810,
    "S1 Ultra-Rare": 7,
    "S1 Common": 62,
    "S2 Epic": 17,
    "S1 Epic": 10,
    "S2 Common": 72,
    "S2 Ultra-Rare": 5,
    "S2 Uncommon": 18,
    "S3 Legendary": 1118,
    "S3 Uncommon": 46,
    "S3 Common": 122,
    "S3 Rare": 55,
    "S3 Epic": 75,
    "S3 Ultra-Rare": 458,
    "S2 Rare": 1
  },
  {
    "Nation": "Thelandoffunfunfun",
    "Junk Value": 1100.52,
    "Bank": 1430.59,
    "Deck Value": 107639.97,
    "Card Count": 3661,
    "Deck Capacity": 3885,
    "Common": 1042,
    "Legendary": 821,
    "Epic": 215,
    "Uncommon": 340,
    "Ultra-Rare": 723,
    "Rare": 520,
    "S1": 53,
    "S2": 634,
    "S3": 2974,
    "S1 Common": 10,
    "S1 Legendary": 13,
    "S2 Common": 310,
    "S2 Epic": 11,
    "S2 Uncommon": 151,
    "S2 Ultra-Rare": 33,
    "S2 Legendary": 122,
    "S2 Rare": 7,
    "S1 Epic": 11,
    "S1 Uncommon": 14,
    "S3 Rare": 511,
    "S3 Uncommon": 175,
    "S3 Legendary": 686,
    "S3 Common": 722,
    "S3 Ultra-Rare": 687,
    "S3 Epic": 193,
    "S1 Rare": 2,
    "S1 Ultra-Rare": 3
  },
  {
    "Nation": "Osheiga",
    "Junk Value": 1381.51,
    "Bank": 8209.28,
    "Deck Value": 106264.86,
    "Card Count": 2730,
    "Deck Capacity": 1546,
    "Rare": 142,
    "Legendary": 1203,
    "Epic": 266,
    "Common": 726,
    "Uncommon": 269,
    "Ultra-Rare": 124,
    "S1": 267,
    "S2": 453,
    "S3": 2010,
    "S1 Rare": 3,
    "S1 Legendary": 185,
    "S1 Epic": 3,
    "S1 Common": 61,
    "S1 Uncommon": 15,
    "S2 Legendary": 179,
    "S2 Epic": 34,
    "S2 Ultra-Rare": 52,
    "S2 Common": 75,
    "S2 Rare": 37,
    "S2 Uncommon": 76,
    "S3 Common": 590,
    "S3 Rare": 102,
    "S3 Ultra-Rare": 72,
    "S3 Epic": 229,
    "S3 Legendary": 839,
    "S3 Uncommon": 178
  },
  {
    "Nation": "Riemstagrad",
    "Junk Value": 6711,
    "Bank": 2918.13,
    "Deck Value": 101438.55,
    "Card Count": 13452,
    "Deck Capacity": 6936,
    "Epic": 11013,
    "Legendary": 1076,
    "Uncommon": 204,
    "Rare": 102,
    "Common": 490,
    "Ultra-Rare": 567,
    "S1": 4218,
    "S2": 5143,
    "S3": 4091,
    "S1 Epic": 3840,
    "S1 Legendary": 234,
    "S2 Legendary": 298,
    "S1 Uncommon": 37,
    "S1 Rare": 20,
    "S1 Common": 38,
    "S2 Epic": 4200,
    "S1 Ultra-Rare": 49,
    "S2 Uncommon": 69,
    "S2 Ultra-Rare": 403,
    "S2 Common": 149,
    "S2 Rare": 24,
    "S3 Epic": 2973,
    "S3 Legendary": 544,
    "S3 Common": 303,
    "S3 Rare": 58,
    "S3 Uncommon": 98,
    "S3 Ultra-Rare": 115
  },
  {
    "Nation": "Second Best Card Collector",
    "Junk Value": 806.63,
    "Bank": 1725.19,
    "Deck Value": 99333.56,
    "Card Count": 10751,
    "Deck Capacity": 6181,
    "Uncommon": 1109,
    "Rare": 1560,
    "Common": 6278,
    "Legendary": 90,
    "Epic": 852,
    "Ultra-Rare": 862,
    "S2": 1413,
    "S1": 175,
    "S3": 9163,
    "S2 Uncommon": 243,
    "S2 Rare": 579,
    "S1 Common": 43,
    "S2 Common": 532,
    "S1 Uncommon": 58,
    "S2 Legendary": 44,
    "S2 Epic": 12,
    "S3 Common": 5703,
    "S3 Uncommon": 808,
    "S3 Ultra-Rare": 847,
    "S3 Rare": 977,
    "S3 Epic": 828,
    "S1 Ultra-Rare": 12,
    "S1 Rare": 4,
    "S1 Epic": 12,
    "S1 Legendary": 46,
    "S2 Ultra-Rare": 3
  },
  {
    "Nation": "9003",
    "Junk Value": 3531.88,
    "Bank": 6607.07,
    "Deck Value": 99283.99,
    "Card Count": 283144,
    "Deck Capacity": 65505,
    "Common": 275828,
    "Rare": 1582,
    "Ultra-Rare": 641,
    "Uncommon": 4338,
    "Epic": 653,
    "Legendary": 102,
    "S2": 257496,
    "S1": 25648,
    "S2 Common": 253943,
    "S1 Common": 21885,
    "S1 Rare": 947,
    "S1 Ultra-Rare": 335,
    "S1 Uncommon": 2153,
    "S1 Epic": 318,
    "S2 Rare": 635,
    "S2 Uncommon": 2185,
    "S2 Epic": 335,
    "S1 Legendary": 10,
    "S2 Ultra-Rare": 306,
    "S2 Legendary": 92
  },
  {
    "Nation": "The Shaymen",
    "Junk Value": 1921,
    "Bank": 1127.89,
    "Deck Value": 95717.35,
    "Card Count": 1921,
    "Deck Capacity": 2005,
    "Legendary": 1921,
    "S1": 56,
    "S2": 759,
    "S3": 1106,
    "S1 Legendary": 56,
    "S2 Legendary": 759,
    "S3 Legendary": 1106
  },
  {
    "Nation": "Ioavollr",
    "Junk Value": 1609.7,
    "Bank": 379.29,
    "Deck Value": 91504.04,
    "Card Count": 3098,
    "Deck Capacity": 5864,
    "Ultra-Rare": 549,
    "Epic": 954,
    "Legendary": 1012,
    "Uncommon": 148,
    "Common": 350,
    "Rare": 85,
    "S1": 277,
    "S2": 1192,
    "S3": 1629,
    "S1 Ultra-Rare": 66,
    "S1 Epic": 45,
    "S1 Legendary": 87,
    "S1 Uncommon": 38,
    "S1 Common": 24,
    "S1 Rare": 17,
    "S2 Uncommon": 69,
    "S2 Ultra-Rare": 325,
    "S2 Legendary": 582,
    "S2 Common": 97,
    "S2 Epic": 90,
    "S2 Rare": 29,
    "S3 Rare": 39,
    "S3 Common": 229,
    "S3 Uncommon": 41,
    "S3 Ultra-Rare": 158,
    "S3 Epic": 819,
    "S3 Legendary": 343
  },
  {
    "Nation": "Minskiev",
    "Junk Value": 1192.26,
    "Bank": 704.77,
    "Deck Value": 81362.22,
    "Card Count": 2281,
    "Deck Capacity": 6344,
    "Legendary": 1113,
    "Epic": 91,
    "Uncommon": 291,
    "Ultra-Rare": 62,
    "Rare": 43,
    "Common": 681,
    "S1": 233,
    "S2": 1399,
    "S3": 649,
    "S1 Legendary": 172,
    "S1 Epic": 21,
    "S1 Uncommon": 20,
    "S1 Ultra-Rare": 6,
    "S2 Legendary": 911,
    "S1 Rare": 3,
    "S2 Common": 322,
    "S2 Ultra-Rare": 33,
    "S2 Uncommon": 64,
    "S2 Rare": 11,
    "S2 Epic": 58,
    "S1 Common": 11,
    "S3 Common": 348,
    "S3 Uncommon": 207,
    "S3 Ultra-Rare": 23,
    "S3 Legendary": 30,
    "S3 Epic": 12,
    "S3 Rare": 29
  },
  {
    "Nation": "Aragesh",
    "Junk Value": 1350.46,
    "Bank": 1266.54,
    "Deck Value": 80669.16,
    "Card Count": 3483,
    "Deck Capacity": 1892,
    "Uncommon": 456,
    "Legendary": 892,
    "Epic": 570,
    "Ultra-Rare": 735,
    "Common": 366,
    "Rare": 464,
    "S1": 490,
    "S2": 1119,
    "S3": 1874,
    "S1 Uncommon": 94,
    "S2 Legendary": 127,
    "S2 Epic": 148,
    "S1 Ultra-Rare": 138,
    "S2 Common": 322,
    "S1 Epic": 108,
    "S1 Rare": 84,
    "S2 Ultra-Rare": 206,
    "S2 Rare": 155,
    "S1 Legendary": 64,
    "S1 Common": 2,
    "S2 Uncommon": 161,
    "S3 Ultra-Rare": 391,
    "S3 Legendary": 701,
    "S3 Uncommon": 201,
    "S3 Common": 42,
    "S3 Rare": 225,
    "S3 Epic": 314
  },
  {
    "Nation": "Siwale",
    "Junk Value": 1158.51,
    "Bank": 2776.18,
    "Deck Value": 80626.63,
    "Card Count": 1401,
    "Deck Capacity": 3186,
    "Common": 71,
    "Legendary": 1066,
    "Ultra-Rare": 61,
    "Epic": 156,
    "Uncommon": 32,
    "Rare": 15,
    "S1": 718,
    "S2": 218,
    "S3": 465,
    "S1 Common": 70,
    "S1 Legendary": 407,
    "S2 Legendary": 213,
    "S1 Ultra-Rare": 58,
    "S1 Epic": 143,
    "S1 Uncommon": 27,
    "S1 Rare": 13,
    "S2 Uncommon": 4,
    "S2 Epic": 1,
    "S3 Legendary": 446,
    "S3 Epic": 12,
    "S3 Rare": 2,
    "S3 Ultra-Rare": 3,
    "S3 Uncommon": 1,
    "S3 Common": 1
  },
  {
    "Nation": "East Chimore",
    "Junk Value": 3774.17,
    "Bank": 696.58,
    "Deck Value": 77861.51,
    "Card Count": 9976,
    "Deck Capacity": 5168,
    "Uncommon": 756,
    "Rare": 519,
    "Epic": 5699,
    "Ultra-Rare": 185,
    "Common": 1987,
    "Legendary": 830,
    "S1": 55,
    "S2": 104,
    "S3": 9817,
    "S1 Uncommon": 10,
    "S1 Rare": 6,
    "S1 Epic": 17,
    "S2 Ultra-Rare": 13,
    "S2 Epic": 15,
    "S2 Uncommon": 32,
    "S2 Common": 30,
    "S2 Rare": 12,
    "S3 Common": 1942,
    "S3 Epic": 5667,
    "S3 Rare": 501,
    "S3 Ultra-Rare": 168,
    "S3 Uncommon": 714,
    "S3 Legendary": 825,
    "S1 Common": 15,
    "S1 Ultra-Rare": 4,
    "S1 Legendary": 3,
    "S2 Legendary": 2
  },
  {
    "Nation": "The Overseer",
    "Junk Value": 1192.45,
    "Bank": 168.55,
    "Deck Value": 77520.4,
    "Card Count": 1607,
    "Deck Capacity": 1000,
    "Ultra-Rare": 138,
    "Legendary": 1149,
    "Epic": 21,
    "Common": 215,
    "Uncommon": 64,
    "Rare": 20,
    "S1": 18,
    "S2": 49,
    "S3": 1540,
    "S1 Ultra-Rare": 3,
    "S1 Legendary": 10,
    "S1 Epic": 1,
    "S1 Common": 2,
    "S2 Legendary": 20,
    "S2 Ultra-Rare": 16,
    "S2 Uncommon": 5,
    "S2 Common": 5,
    "S2 Epic": 1,
    "S2 Rare": 2,
    "S1 Rare": 1,
    "S3 Common": 208,
    "S3 Uncommon": 58,
    "S3 Legendary": 1119,
    "S3 Ultra-Rare": 119,
    "S3 Rare": 17,
    "S3 Epic": 19,
    "S1 Uncommon": 1
  },
  {
    "Nation": "Ever Testing",
    "Junk Value": 4609.69,
    "Bank": 1482.97,
    "Deck Value": 75369.53,
    "Card Count": 13672,
    "Deck Capacity": 7037,
    "Common": 3969,
    "Epic": 7184,
    "Uncommon": 712,
    "Rare": 399,
    "Ultra-Rare": 582,
    "Legendary": 826,
    "S1": 277,
    "S2": 3658,
    "S3": 9737,
    "S1 Common": 156,
    "S1 Epic": 80,
    "S2 Epic": 1847,
    "S2 Common": 1365,
    "S1 Uncommon": 20,
    "S2 Uncommon": 145,
    "S2 Rare": 58,
    "S2 Ultra-Rare": 59,
    "S2 Legendary": 184,
    "S1 Ultra-Rare": 9,
    "S1 Rare": 6,
    "S1 Legendary": 6,
    "S3 Common": 2448,
    "S3 Uncommon": 547,
    "S3 Epic": 5257,
    "S3 Rare": 335,
    "S3 Ultra-Rare": 514,
    "S3 Legendary": 636
  },
  {
    "Nation": "Dr Hooves",
    "Junk Value": 1103.32,
    "Bank": 15603.28,
    "Deck Value": 74924.98,
    "Card Count": 4188,
    "Deck Capacity": 4931,
    "Common": 1602,
    "Uncommon": 1016,
    "Rare": 355,
    "Ultra-Rare": 170,
    "Epic": 85,
    "Legendary": 960,
    "S1": 296,
    "S2": 1062,
    "S3": 2830,
    "S1 Common": 128,
    "S2 Common": 386,
    "S1 Uncommon": 91,
    "S2 Uncommon": 384,
    "S2 Rare": 75,
    "S1 Ultra-Rare": 15,
    "S1 Rare": 35,
    "S1 Epic": 8,
    "S1 Legendary": 19,
    "S2 Ultra-Rare": 27,
    "S2 Legendary": 177,
    "S2 Epic": 13,
    "S3 Uncommon": 541,
    "S3 Ultra-Rare": 128,
    "S3 Common": 1088,
    "S3 Rare": 245,
    "S3 Legendary": 764,
    "S3 Epic": 64
  },
  {
    "Nation": "New Kowloon Bay",
    "Junk Value": 1130.2,
    "Bank": 728.46,
    "Deck Value": 73576.74,
    "Card Count": 2655,
    "Deck Capacity": 2779,
    "Legendary": 867,
    "Epic": 222,
    "Common": 640,
    "Ultra-Rare": 710,
    "Uncommon": 76,
    "Rare": 140,
    "S1": 261,
    "S2": 904,
    "S3": 1490,
    "S1 Legendary": 40,
    "S1 Epic": 66,
    "S2 Legendary": 275,
    "S2 Epic": 91,
    "S1 Common": 21,
    "S1 Ultra-Rare": 115,
    "S1 Uncommon": 19,
    "S2 Ultra-Rare": 303,
    "S2 Common": 214,
    "S2 Uncommon": 18,
    "S2 Rare": 3,
    "S3 Legendary": 552,
    "S3 Common": 405,
    "S3 Uncommon": 39,
    "S3 Ultra-Rare": 292,
    "S3 Epic": 65,
    "S3 Rare": 137
  },
  {
    "Nation": "Laudesia",
    "Junk Value": 1069.14,
    "Bank": 2046.79,
    "Deck Value": 68341.05,
    "Card Count": 4642,
    "Deck Capacity": 4931,
    "Common": 2309,
    "Legendary": 893,
    "Rare": 182,
    "Uncommon": 993,
    "Epic": 168,
    "Ultra-Rare": 97,
    "S1": 759,
    "S2": 1104,
    "S3": 2779,
    "S1 Common": 450,
    "S1 Legendary": 95,
    "S1 Rare": 27,
    "S1 Uncommon": 130,
    "S1 Epic": 24,
    "S1 Ultra-Rare": 33,
    "S2 Common": 217,
    "S2 Legendary": 499,
    "S2 Uncommon": 334,
    "S2 Ultra-Rare": 26,
    "S2 Rare": 5,
    "S2 Epic": 23,
    "S3 Common": 1642,
    "S3 Rare": 150,
    "S3 Uncommon": 529,
    "S3 Legendary": 299,
    "S3 Epic": 121,
    "S3 Ultra-Rare": 38
  },
  {
    "Nation": "Bawkie",
    "Junk Value": 685.74,
    "Bank": 1749.98,
    "Deck Value": 66980.43,
    "Card Count": 1823,
    "Deck Capacity": 2779,
    "Uncommon": 133,
    "Legendary": 620,
    "Epic": 95,
    "Rare": 253,
    "Ultra-Rare": 23,
    "Common": 699,
    "S1": 184,
    "S2": 797,
    "S3": 842,
    "S1 Uncommon": 78,
    "S1 Legendary": 72,
    "S1 Epic": 21,
    "S2 Rare": 251,
    "S1 Ultra-Rare": 9,
    "S1 Common": 2,
    "S2 Epic": 24,
    "S2 Legendary": 318,
    "S2 Ultra-Rare": 10,
    "S2 Common": 177,
    "S2 Uncommon": 17,
    "S1 Rare": 2,
    "S3 Common": 520,
    "S3 Legendary": 230,
    "S3 Epic": 50,
    "S3 Uncommon": 38,
    "S3 Ultra-Rare": 4
  },
  {
    "Nation": "Triseria",
    "Junk Value": 1139.96,
    "Bank": 1668.31,
    "Deck Value": 66126.25,
    "Card Count": 2119,
    "Deck Capacity": 5864,
    "Legendary": 1109,
    "Common": 756,
    "Uncommon": 124,
    "Rare": 89,
    "Epic": 30,
    "Ultra-Rare": 11,
    "S1": 73,
    "S2": 590,
    "S3": 1456,
    "S1 Legendary": 69,
    "S2 Legendary": 575,
    "S2 Common": 8,
    "S2 Uncommon": 3,
    "S2 Rare": 2,
    "S2 Epic": 2,
    "S3 Legendary": 465,
    "S3 Common": 748,
    "S3 Uncommon": 117,
    "S3 Ultra-Rare": 11,
    "S3 Rare": 87,
    "S3 Epic": 28,
    "S1 Uncommon": 4
  },
  {
    "Nation": "Apexiala",
    "Junk Value": 1682,
    "Bank": 2468.18,
    "Deck Value": 60686.81,
    "Card Count": 39007,
    "Deck Capacity": 19642,
    "Ultra-Rare": 1136,
    "Common": 29985,
    "Uncommon": 5089,
    "Rare": 1635,
    "Legendary": 639,
    "Epic": 523,
    "S1": 856,
    "S2": 13962,
    "S3": 24189,
    "S1 Ultra-Rare": 70,
    "S2 Common": 9790,
    "S1 Common": 395,
    "S1 Uncommon": 231,
    "S2 Uncommon": 2276,
    "S1 Rare": 110,
    "S1 Legendary": 21,
    "S1 Epic": 29,
    "S2 Ultra-Rare": 508,
    "S2 Epic": 273,
    "S2 Legendary": 375,
    "S2 Rare": 740,
    "S3 Common": 19800,
    "S3 Rare": 785,
    "S3 Uncommon": 2582,
    "S3 Legendary": 243,
    "S3 Ultra-Rare": 558,
    "S3 Epic": 221
  },
  {
    "Nation": "The Atlae Isles",
    "Junk Value": 880.93,
    "Bank": 30.06,
    "Deck Value": 53397.57,
    "Card Count": 3926,
    "Deck Capacity": 5393,
    "Rare": 99,
    "Epic": 240,
    "Ultra-Rare": 471,
    "Common": 2213,
    "Legendary": 631,
    "Uncommon": 272,
    "S1": 569,
    "S2": 1750,
    "S3": 1607,
    "S1 Rare": 34,
    "S1 Epic": 82,
    "S2 Ultra-Rare": 333,
    "S1 Common": 105,
    "S1 Ultra-Rare": 117,
    "S1 Legendary": 137,
    "S1 Uncommon": 94,
    "S2 Common": 701,
    "S2 Uncommon": 85,
    "S2 Epic": 124,
    "S2 Legendary": 461,
    "S2 Rare": 46,
    "S3 Common": 1407,
    "S3 Uncommon": 93,
    "S3 Ultra-Rare": 21,
    "S3 Legendary": 33,
    "S3 Epic": 34,
    "S3 Rare": 19
  },
  {
    "Nation": "One Small Island",
    "Junk Value": 730.01,
    "Bank": 176.93,
    "Deck Value": 51173.15,
    "Card Count": 1607,
    "Deck Capacity": 4037,
    "Legendary": 646,
    "Common": 616,
    "Uncommon": 167,
    "Epic": 131,
    "Rare": 27,
    "Ultra-Rare": 20,
    "S1": 270,
    "S2": 1291,
    "S3": 46,
    "S1 Legendary": 81,
    "S1 Common": 70,
    "S1 Uncommon": 17,
    "S1 Epic": 89,
    "S2 Epic": 36,
    "S2 Common": 543,
    "S2 Legendary": 532,
    "S1 Rare": 4,
    "S1 Ultra-Rare": 9,
    "S2 Uncommon": 149,
    "S2 Rare": 22,
    "S2 Ultra-Rare": 9,
    "S3 Legendary": 33,
    "S3 Epic": 6,
    "S3 Uncommon": 1,
    "S3 Ultra-Rare": 2,
    "S3 Common": 3,
    "S3 Rare": 1
  },
  {
    "Nation": "Elegarth",
    "Junk Value": 641.16,
    "Bank": 544.24,
    "Deck Value": 50184.79,
    "Card Count": 1487,
    "Deck Capacity": 4479,
    "Uncommon": 150,
    "Legendary": 572,
    "Common": 186,
    "Ultra-Rare": 239,
    "Epic": 24,
    "Rare": 316,
    "S1": 349,
    "S2": 777,
    "S3": 361,
    "S1 Uncommon": 64,
    "S1 Legendary": 191,
    "S1 Common": 64,
    "S2 Legendary": 289,
    "S1 Ultra-Rare": 13,
    "S1 Epic": 12,
    "S1 Rare": 5,
    "S2 Common": 97,
    "S2 Ultra-Rare": 68,
    "S2 Rare": 289,
    "S2 Epic": 6,
    "S2 Uncommon": 28,
    "S3 Ultra-Rare": 158,
    "S3 Legendary": 92,
    "S3 Common": 25,
    "S3 Epic": 6,
    "S3 Uncommon": 58,
    "S3 Rare": 22
  },
  {
    "Nation": "Benevolent 1",
    "Junk Value": 579.02,
    "Bank": 12589.07,
    "Deck Value": 49953.58,
    "Card Count": 2494,
    "Deck Capacity": 3186,
    "Epic": 156,
    "Uncommon": 484,
    "Common": 1042,
    "Legendary": 432,
    "Rare": 208,
    "Ultra-Rare": 172,
    "S1": 1082,
    "S2": 739,
    "S3": 673,
    "S1 Epic": 90,
    "S1 Uncommon": 180,
    "S1 Common": 507,
    "S1 Legendary": 136,
    "S2 Uncommon": 206,
    "S1 Rare": 115,
    "S1 Ultra-Rare": 54,
    "S2 Common": 273,
    "S2 Rare": 36,
    "S2 Legendary": 176,
    "S2 Ultra-Rare": 18,
    "S2 Epic": 30,
    "S3 Ultra-Rare": 100,
    "S3 Legendary": 120,
    "S3 Rare": 57,
    "S3 Common": 262,
    "S3 Epic": 36,
    "S3 Uncommon": 98
  },
  {
    "Nation": "Refuge Isle",
    "Junk Value": 1902.85,
    "Bank": 635.26,
    "Deck Value": 49392.62,
    "Card Count": 6173,
    "Deck Capacity": 7330,
    "Ultra-Rare": 4759,
    "Legendary": 796,
    "Common": 210,
    "Rare": 49,
    "Epic": 300,
    "Uncommon": 59,
    "S1": 5191,
    "S2": 663,
    "S3": 319,
    "S1 Ultra-Rare": 4711,
    "S1 Legendary": 171,
    "S2 Common": 107,
    "S1 Rare": 19,
    "S1 Epic": 238,
    "S2 Rare": 21,
    "S1 Uncommon": 22,
    "S1 Common": 30,
    "S2 Epic": 20,
    "S2 Uncommon": 29,
    "S2 Ultra-Rare": 29,
    "S2 Legendary": 457,
    "S3 Rare": 9,
    "S3 Legendary": 168,
    "S3 Ultra-Rare": 19,
    "S3 Common": 73,
    "S3 Epic": 42,
    "S3 Uncommon": 8
  },
  {
    "Nation": "The Bank Of Caprica",
    "Junk Value": 25.05,
    "Bank": 39.89,
    "Deck Value": 48972.39,
    "Card Count": 1610,
    "Deck Capacity": 1296,
    "Common": 895,
    "Uncommon": 308,
    "Rare": 405,
    "Ultra-Rare": 1,
    "Epic": 1,
    "S2": 847,
    "S1": 1,
    "S3": 762,
    "S2 Common": 697,
    "S2 Uncommon": 150,
    "S1 Uncommon": 1,
    "S3 Common": 198,
    "S3 Uncommon": 157,
    "S3 Rare": 405,
    "S3 Ultra-Rare": 1,
    "S3 Epic": 1
  },
  {
    "Nation": "Fauzjhia",
    "Junk Value": 2239.8,
    "Bank": 40306.84,
    "Deck Value": 47234.71,
    "Card Count": 4974,
    "Deck Capacity": 5393,
    "Epic": 4220,
    "Ultra-Rare": 424,
    "Legendary": 30,
    "Uncommon": 300,
    "S1": 537,
    "S2": 737,
    "S3": 3700,
    "S1 Epic": 445,
    "S1 Ultra-Rare": 79,
    "S1 Legendary": 13,
    "S2 Ultra-Rare": 94,
    "S2 Epic": 343,
    "S2 Uncommon": 300,
    "S3 Epic": 3432,
    "S3 Ultra-Rare": 251,
    "S3 Legendary": 17
  },
  {
    "Nation": "Valoptia",
    "Junk Value": 607.07,
    "Bank": 465.44,
    "Deck Value": 45889.29,
    "Card Count": 763,
    "Deck Capacity": 668,
    "Legendary": 607,
    "Common": 7,
    "Rare": 149,
    "S1": 184,
    "S2": 177,
    "S3": 402,
    "S1 Legendary": 184,
    "S2 Legendary": 171,
    "S2 Common": 6,
    "S3 Rare": 149,
    "S3 Legendary": 252,
    "S3 Common": 1
  },
  {
    "Nation": "Andusre",
    "Junk Value": 793.95,
    "Bank": 1609.97,
    "Deck Value": 45265.52,
    "Card Count": 1040,
    "Deck Capacity": 3186,
    "Common": 115,
    "Legendary": 777,
    "Uncommon": 76,
    "Ultra-Rare": 30,
    "Epic": 12,
    "Rare": 30,
    "S1": 73,
    "S2": 788,
    "S3": 179,
    "S1 Common": 2,
    "S2 Legendary": 647,
    "S1 Legendary": 68,
    "S1 Uncommon": 2,
    "S2 Uncommon": 49,
    "S2 Common": 50,
    "S2 Ultra-Rare": 24,
    "S1 Epic": 1,
    "S2 Epic": 5,
    "S2 Rare": 13,
    "S3 Common": 63,
    "S3 Uncommon": 25,
    "S3 Legendary": 62,
    "S3 Rare": 17,
    "S3 Ultra-Rare": 6,
    "S3 Epic": 6
  },
  {
    "Nation": "Giraffeton",
    "Junk Value": 1428.02,
    "Bank": 4137.29,
    "Deck Value": 43175.48,
    "Card Count": 30100,
    "Deck Capacity": 15970,
    "Uncommon": 4518,
    "Common": 21232,
    "Ultra-Rare": 2004,
    "Rare": 1395,
    "Epic": 724,
    "Legendary": 227,
    "S1": 56,
    "S2": 3982,
    "S3": 26062,
    "S1 Uncommon": 15,
    "S1 Common": 24,
    "S2 Uncommon": 830,
    "S2 Ultra-Rare": 852,
    "S2 Rare": 279,
    "S2 Epic": 273,
    "S2 Common": 1681,
    "S1 Rare": 5,
    "S2 Legendary": 67,
    "S1 Ultra-Rare": 6,
    "S1 Epic": 4,
    "S3 Ultra-Rare": 1146,
    "S3 Rare": 1111,
    "S3 Epic": 447,
    "S3 Common": 19527,
    "S3 Uncommon": 3673,
    "S3 Legendary": 158,
    "S1 Legendary": 2
  },
  {
    "Nation": "Midlands",
    "Junk Value": 1781.57,
    "Bank": 4987.29,
    "Deck Value": 42926.49,
    "Card Count": 6419,
    "Deck Capacity": 4479,
    "Epic": 1006,
    "Ultra-Rare": 2086,
    "Legendary": 796,
    "Rare": 750,
    "Common": 592,
    "Uncommon": 1189,
    "S1": 183,
    "S2": 1440,
    "S3": 4796,
    "S1 Epic": 45,
    "S1 Ultra-Rare": 28,
    "S1 Legendary": 60,
    "S1 Rare": 10,
    "S1 Common": 9,
    "S1 Uncommon": 31,
    "S2 Legendary": 711,
    "S2 Uncommon": 168,
    "S2 Ultra-Rare": 209,
    "S2 Rare": 137,
    "S2 Epic": 191,
    "S2 Common": 24,
    "S3 Ultra-Rare": 1849,
    "S3 Common": 559,
    "S3 Uncommon": 990,
    "S3 Legendary": 25,
    "S3 Rare": 603,
    "S3 Epic": 770
  },
  {
    "Nation": "Humansanity",
    "Junk Value": 591.06,
    "Bank": 917.61,
    "Deck Value": 42423.38,
    "Card Count": 892,
    "Deck Capacity": 3186,
    "Legendary": 538,
    "Uncommon": 59,
    "Rare": 96,
    "Ultra-Rare": 65,
    "Epic": 73,
    "Common": 61,
    "S1": 84,
    "S2": 772,
    "S3": 36,
    "S1 Legendary": 51,
    "S2 Uncommon": 45,
    "S1 Uncommon": 5,
    "S2 Rare": 87,
    "S2 Ultra-Rare": 45,
    "S2 Legendary": 485,
    "S1 Epic": 8,
    "S1 Ultra-Rare": 12,
    "S1 Common": 6,
    "S1 Rare": 2,
    "S2 Epic": 58,
    "S2 Common": 52,
    "S3 Uncommon": 9,
    "S3 Rare": 7,
    "S3 Ultra-Rare": 8,
    "S3 Common": 3,
    "S3 Epic": 7,
    "S3 Legendary": 2
  },
  {
    "Nation": "Drew Durrnil",
    "Junk Value": 801.32,
    "Bank": 1.82,
    "Deck Value": 42292.3,
    "Card Count": 2963,
    "Deck Capacity": 3005,
    "Epic": 257,
    "Ultra-Rare": 288,
    "Common": 947,
    "Legendary": 578,
    "Rare": 338,
    "Uncommon": 555,
    "S1": 41,
    "S2": 309,
    "S3": 2613,
    "S1 Epic": 2,
    "S1 Ultra-Rare": 5,
    "S1 Common": 18,
    "S2 Legendary": 14,
    "S2 Rare": 42,
    "S2 Epic": 39,
    "S2 Ultra-Rare": 105,
    "S2 Uncommon": 50,
    "S2 Common": 59,
    "S1 Rare": 11,
    "S1 Uncommon": 4,
    "S3 Uncommon": 501,
    "S3 Epic": 216,
    "S3 Ultra-Rare": 178,
    "S3 Common": 870,
    "S3 Rare": 285,
    "S3 Legendary": 563,
    "S1 Legendary": 1
  },
  {
    "Nation": "Sylh Alanor",
    "Junk Value": 392.48,
    "Bank": 352.94,
    "Deck Value": 42265.74,
    "Card Count": 518,
    "Deck Capacity": 3186,
    "Legendary": 368,
    "Common": 73,
    "Rare": 10,
    "Epic": 39,
    "Ultra-Rare": 19,
    "Uncommon": 9,
    "S1": 169,
    "S2": 311,
    "S3": 38,
    "S1 Legendary": 152,
    "S2 Common": 68,
    "S1 Rare": 3,
    "S2 Epic": 25,
    "S2 Legendary": 205,
    "S1 Epic": 6,
    "S1 Ultra-Rare": 6,
    "S2 Uncommon": 3,
    "S2 Ultra-Rare": 8,
    "S2 Rare": 2,
    "S1 Uncommon": 2,
    "S3 Legendary": 11,
    "S3 Common": 5,
    "S3 Rare": 5,
    "S3 Ultra-Rare": 5,
    "S3 Uncommon": 4,
    "S3 Epic": 8
  },
  {
    "Nation": "Ballotonia",
    "Junk Value": 1152.96,
    "Bank": 1595.78,
    "Deck Value": 41438.12,
    "Card Count": 5475,
    "Deck Capacity": 6344,
    "Uncommon": 1339,
    "Common": 981,
    "Ultra-Rare": 1091,
    "Rare": 867,
    "Epic": 678,
    "Legendary": 519,
    "S1": 3637,
    "S2": 833,
    "S3": 1005,
    "S1 Uncommon": 1053,
    "S1 Common": 658,
    "S1 Ultra-Rare": 726,
    "S1 Rare": 600,
    "S2 Epic": 124,
    "S1 Epic": 416,
    "S1 Legendary": 184,
    "S2 Rare": 103,
    "S2 Common": 135,
    "S2 Legendary": 169,
    "S2 Ultra-Rare": 167,
    "S2 Uncommon": 135,
    "S3 Rare": 164,
    "S3 Ultra-Rare": 198,
    "S3 Legendary": 166,
    "S3 Common": 188,
    "S3 Uncommon": 151,
    "S3 Epic": 138
  },
  {
    "Nation": "New Sunville",
    "Junk Value": 658.52,
    "Bank": 1492.76,
    "Deck Value": 40897.13,
    "Card Count": 2261,
    "Deck Capacity": 5393,
    "Common": 747,
    "Uncommon": 463,
    "Rare": 105,
    "Epic": 193,
    "Ultra-Rare": 277,
    "Legendary": 476,
    "S1": 143,
    "S2": 1121,
    "S3": 997,
    "S1 Common": 26,
    "S1 Uncommon": 27,
    "S1 Rare": 9,
    "S2 Epic": 58,
    "S1 Ultra-Rare": 22,
    "S1 Epic": 30,
    "S1 Legendary": 29,
    "S2 Common": 409,
    "S2 Ultra-Rare": 81,
    "S2 Uncommon": 355,
    "S2 Legendary": 169,
    "S2 Rare": 49,
    "S3 Common": 312,
    "S3 Legendary": 278,
    "S3 Uncommon": 81,
    "S3 Ultra-Rare": 174,
    "S3 Epic": 105,
    "S3 Rare": 47
  },
  {
    "Nation": "Waterfall State",
    "Junk Value": 798.48,
    "Bank": 995.67,
    "Deck Value": 40467.77,
    "Card Count": 4918,
    "Deck Capacity": 2779,
    "Common": 3248,
    "Uncommon": 488,
    "Rare": 257,
    "Legendary": 647,
    "Ultra-Rare": 148,
    "Epic": 130,
    "S1": 830,
    "S2": 1441,
    "S3": 2647,
    "S1 Common": 290,
    "S1 Uncommon": 265,
    "S1 Rare": 173,
    "S2 Legendary": 194,
    "S1 Ultra-Rare": 69,
    "S2 Common": 846,
    "S1 Epic": 23,
    "S1 Legendary": 10,
    "S2 Rare": 72,
    "S2 Uncommon": 177,
    "S2 Epic": 87,
    "S2 Ultra-Rare": 65,
    "S3 Common": 2112,
    "S3 Legendary": 443,
    "S3 Ultra-Rare": 14,
    "S3 Rare": 12,
    "S3 Uncommon": 46,
    "S3 Epic": 20
  },
  {
    "Nation": "Shibutani",
    "Junk Value": 650.96,
    "Bank": 93.31,
    "Deck Value": 40361.73,
    "Card Count": 2222,
    "Deck Capacity": 4037,
    "Legendary": 459,
    "Epic": 225,
    "Ultra-Rare": 262,
    "Uncommon": 408,
    "Common": 666,
    "Rare": 202,
    "S1": 312,
    "S2": 437,
    "S3": 1473,
    "S1 Legendary": 135,
    "S1 Epic": 87,
    "S1 Ultra-Rare": 54,
    "S1 Uncommon": 16,
    "S2 Legendary": 139,
    "S2 Common": 172,
    "S1 Rare": 5,
    "S1 Common": 15,
    "S2 Uncommon": 49,
    "S2 Ultra-Rare": 42,
    "S2 Epic": 30,
    "S2 Rare": 5,
    "S3 Common": 479,
    "S3 Epic": 108,
    "S3 Legendary": 185,
    "S3 Uncommon": 343,
    "S3 Ultra-Rare": 166,
    "S3 Rare": 192
  },
  {
    "Nation": "Klaus Devestatorie",
    "Junk Value": 2893.69,
    "Bank": 3180.45,
    "Deck Value": 39113.41,
    "Card Count": 8339,
    "Deck Capacity": 4296,
    "Ultra-Rare": 1201,
    "Common": 1114,
    "Epic": 4262,
    "Rare": 598,
    "Uncommon": 687,
    "Legendary": 477,
    "S1": 514,
    "S2": 110,
    "S3": 7715,
    "S1 Ultra-Rare": 184,
    "S1 Common": 134,
    "S1 Epic": 79,
    "S1 Rare": 32,
    "S1 Uncommon": 75,
    "S1 Legendary": 10,
    "S2 Epic": 38,
    "S2 Uncommon": 33,
    "S2 Rare": 17,
    "S2 Common": 16,
    "S2 Ultra-Rare": 4,
    "S3 Common": 964,
    "S3 Epic": 4145,
    "S3 Uncommon": 579,
    "S3 Legendary": 465,
    "S3 Ultra-Rare": 1013,
    "S3 Rare": 549,
    "S2 Legendary": 2
  },
  {
    "Nation": "Christ Triumphant",
    "Junk Value": 672.27,
    "Bank": 311.66,
    "Deck Value": 38685.71,
    "Card Count": 2964,
    "Deck Capacity": 5393,
    "Epic": 227,
    "Uncommon": 755,
    "Common": 882,
    "Ultra-Rare": 341,
    "Rare": 315,
    "Legendary": 444,
    "S1": 1180,
    "S2": 1032,
    "S3": 752,
    "S1 Epic": 134,
    "S1 Uncommon": 312,
    "S1 Common": 264,
    "S1 Ultra-Rare": 178,
    "S1 Rare": 124,
    "S2 Common": 271,
    "S2 Uncommon": 271,
    "S2 Ultra-Rare": 111,
    "S1 Legendary": 168,
    "S2 Rare": 113,
    "S2 Legendary": 214,
    "S2 Epic": 52,
    "S3 Uncommon": 172,
    "S3 Common": 347,
    "S3 Legendary": 62,
    "S3 Ultra-Rare": 52,
    "S3 Rare": 78,
    "S3 Epic": 41
  },
  {
    "Nation": "Yodle",
    "Junk Value": 942.5,
    "Bank": 360.26,
    "Deck Value": 37385.26,
    "Card Count": 18628,
    "Deck Capacity": 9287,
    "Uncommon": 5451,
    "Common": 8295,
    "Rare": 2705,
    "Ultra-Rare": 1725,
    "Epic": 420,
    "Legendary": 32,
    "S1": 2418,
    "S2": 8705,
    "S3": 7505,
    "S1 Uncommon": 563,
    "S1 Common": 1410,
    "S1 Rare": 237,
    "S1 Ultra-Rare": 153,
    "S1 Epic": 52,
    "S2 Rare": 1362,
    "S2 Common": 3368,
    "S2 Uncommon": 2816,
    "S2 Ultra-Rare": 1033,
    "S1 Legendary": 3,
    "S2 Epic": 119,
    "S2 Legendary": 7,
    "S3 Epic": 249,
    "S3 Common": 3517,
    "S3 Uncommon": 2072,
    "S3 Legendary": 22,
    "S3 Ultra-Rare": 539,
    "S3 Rare": 1106
  },
  {
    "Nation": "Xoriet",
    "Junk Value": 468.1,
    "Bank": 2922.08,
    "Deck Value": 36758.64,
    "Card Count": 1704,
    "Deck Capacity": 5864,
    "Legendary": 261,
    "Ultra-Rare": 337,
    "Uncommon": 355,
    "Common": 345,
    "Rare": 169,
    "Epic": 237,
    "S1": 1106,
    "S2": 447,
    "S3": 151,
    "S1 Legendary": 125,
    "S1 Ultra-Rare": 219,
    "S1 Uncommon": 255,
    "S1 Common": 200,
    "S1 Rare": 132,
    "S2 Epic": 51,
    "S1 Epic": 175,
    "S2 Common": 107,
    "S2 Ultra-Rare": 87,
    "S2 Uncommon": 83,
    "S2 Legendary": 96,
    "S2 Rare": 23,
    "S3 Rare": 14,
    "S3 Ultra-Rare": 31,
    "S3 Legendary": 40,
    "S3 Uncommon": 17,
    "S3 Epic": 11,
    "S3 Common": 38
  },
  {
    "Nation": "Numero Capitan",
    "Junk Value": 608.83,
    "Bank": 178.88,
    "Deck Value": 35428.53,
    "Card Count": 1749,
    "Deck Capacity": 3186,
    "Rare": 156,
    "Common": 408,
    "Ultra-Rare": 252,
    "Epic": 117,
    "Uncommon": 337,
    "Legendary": 479,
    "S1": 364,
    "S2": 830,
    "S3": 555,
    "S1 Rare": 40,
    "S1 Common": 102,
    "S1 Ultra-Rare": 59,
    "S1 Epic": 35,
    "S1 Uncommon": 65,
    "S2 Legendary": 172,
    "S1 Legendary": 63,
    "S2 Common": 222,
    "S2 Uncommon": 208,
    "S2 Ultra-Rare": 113,
    "S2 Rare": 74,
    "S2 Epic": 41,
    "S3 Uncommon": 64,
    "S3 Ultra-Rare": 80,
    "S3 Rare": 42,
    "S3 Legendary": 244,
    "S3 Common": 84,
    "S3 Epic": 41
  },
  {
    "Nation": "Zakaruba",
    "Junk Value": 1312.99,
    "Bank": 707.06,
    "Deck Value": 34844.99,
    "Card Count": 3870,
    "Deck Capacity": 2000,
    "Rare": 272,
    "Common": 849,
    "Ultra-Rare": 257,
    "Uncommon": 472,
    "Epic": 1581,
    "Legendary": 439,
    "S1": 383,
    "S2": 463,
    "S3": 3024,
    "S1 Rare": 64,
    "S1 Common": 138,
    "S1 Ultra-Rare": 20,
    "S1 Uncommon": 144,
    "S2 Epic": 24,
    "S1 Epic": 15,
    "S2 Common": 243,
    "S2 Ultra-Rare": 24,
    "S2 Rare": 56,
    "S3 Epic": 1542,
    "S3 Uncommon": 215,
    "S3 Common": 468,
    "S3 Legendary": 434,
    "S3 Rare": 152,
    "S3 Ultra-Rare": 213,
    "S1 Legendary": 2,
    "S2 Uncommon": 113,
    "S2 Legendary": 3
  },
  {
    "Nation": "Cavedweller",
    "Junk Value": 353.26,
    "Bank": 1090.18,
    "Deck Value": 32480.15,
    "Card Count": 758,
    "Deck Capacity": 2779,
    "Ultra-Rare": 105,
    "Uncommon": 108,
    "Common": 186,
    "Rare": 23,
    "Epic": 22,
    "Legendary": 314,
    "S1": 142,
    "S2": 605,
    "S3": 11,
    "S1 Ultra-Rare": 16,
    "S1 Uncommon": 34,
    "S1 Common": 26,
    "S1 Rare": 4,
    "S1 Epic": 4,
    "S1 Legendary": 58,
    "S2 Common": 159,
    "S2 Ultra-Rare": 87,
    "S2 Rare": 18,
    "S2 Legendary": 253,
    "S2 Epic": 18,
    "S2 Uncommon": 70,
    "S3 Ultra-Rare": 2,
    "S3 Uncommon": 4,
    "S3 Common": 1,
    "S3 Legendary": 3,
    "S3 Rare": 1
  },
  {
    "Nation": "The Rhein States",
    "Junk Value": 471.87,
    "Bank": 1324.83,
    "Deck Value": 32340.65,
    "Card Count": 872,
    "Deck Capacity": 3606,
    "Legendary": 420,
    "Common": 117,
    "Uncommon": 106,
    "Epic": 58,
    "Ultra-Rare": 82,
    "Rare": 89,
    "S2": 408,
    "S1": 154,
    "S3": 310,
    "S2 Legendary": 185,
    "S1 Legendary": 90,
    "S2 Common": 73,
    "S1 Uncommon": 28,
    "S1 Common": 12,
    "S1 Epic": 11,
    "S1 Ultra-Rare": 9,
    "S1 Rare": 4,
    "S2 Rare": 55,
    "S2 Epic": 24,
    "S2 Uncommon": 65,
    "S2 Ultra-Rare": 6,
    "S3 Ultra-Rare": 67,
    "S3 Legendary": 145,
    "S3 Common": 32,
    "S3 Epic": 23,
    "S3 Rare": 30,
    "S3 Uncommon": 13
  },
  {
    "Nation": "Fastercat",
    "Junk Value": 556.06,
    "Bank": 270.83,
    "Deck Value": 31288.25,
    "Card Count": 2680,
    "Deck Capacity": 1500,
    "Legendary": 120,
    "Common": 506,
    "Epic": 577,
    "Ultra-Rare": 579,
    "Uncommon": 534,
    "Rare": 364,
    "S1": 113,
    "S2": 344,
    "S3": 2223,
    "S1 Legendary": 2,
    "S2 Common": 74,
    "S1 Epic": 18,
    "S1 Ultra-Rare": 29,
    "S2 Uncommon": 139,
    "S1 Rare": 22,
    "S1 Common": 8,
    "S1 Uncommon": 34,
    "S2 Ultra-Rare": 58,
    "S2 Epic": 37,
    "S2 Rare": 34,
    "S2 Legendary": 2,
    "S3 Common": 424,
    "S3 Rare": 308,
    "S3 Epic": 522,
    "S3 Uncommon": 361,
    "S3 Ultra-Rare": 492,
    "S3 Legendary": 116
  },
  {
    "Nation": "Super Awesome Fun Times",
    "Junk Value": 1094.17,
    "Bank": 2117.01,
    "Deck Value": 30298.53,
    "Card Count": 19242,
    "Deck Capacity": 13837,
    "Ultra-Rare": 1060,
    "Rare": 1120,
    "Epic": 452,
    "Uncommon": 5000,
    "Common": 11317,
    "Legendary": 293,
    "S1": 866,
    "S2": 6993,
    "S3": 11383,
    "S1 Ultra-Rare": 118,
    "S1 Rare": 89,
    "S1 Epic": 77,
    "S1 Uncommon": 289,
    "S1 Common": 291,
    "S2 Uncommon": 1583,
    "S2 Ultra-Rare": 343,
    "S2 Common": 4579,
    "S2 Epic": 150,
    "S2 Rare": 296,
    "S1 Legendary": 2,
    "S2 Legendary": 42,
    "S3 Uncommon": 3128,
    "S3 Common": 6447,
    "S3 Rare": 735,
    "S3 Ultra-Rare": 599,
    "S3 Epic": 225,
    "S3 Legendary": 249
  },
  {
    "Nation": "Independent Federation Of Croatia",
    "Junk Value": 610.74,
    "Bank": 239.76,
    "Deck Value": 29318.45,
    "Card Count": 1557,
    "Deck Capacity": 4931,
    "Common": 344,
    "Legendary": 296,
    "Epic": 583,
    "Ultra-Rare": 41,
    "Uncommon": 232,
    "Rare": 61,
    "S1": 643,
    "S2": 338,
    "S3": 576,
    "S1 Common": 131,
    "S1 Legendary": 235,
    "S2 Legendary": 44,
    "S1 Epic": 147,
    "S1 Ultra-Rare": 28,
    "S1 Uncommon": 80,
    "S1 Rare": 22,
    "S2 Epic": 224,
    "S2 Ultra-Rare": 8,
    "S2 Common": 19,
    "S2 Rare": 11,
    "S2 Uncommon": 32,
    "S3 Epic": 212,
    "S3 Rare": 28,
    "S3 Common": 194,
    "S3 Ultra-Rare": 5,
    "S3 Uncommon": 120,
    "S3 Legendary": 17
  },
  {
    "Nation": "Montrandec",
    "Junk Value": 1557.88,
    "Bank": 44.45,
    "Deck Value": 29182.76,
    "Card Count": 4765,
    "Deck Capacity": 2635,
    "Legendary": 508,
    "Ultra-Rare": 404,
    "Common": 943,
    "Epic": 1858,
    "Rare": 439,
    "Uncommon": 613,
    "S1": 398,
    "S2": 915,
    "S3": 3452,
    "S1 Legendary": 11,
    "S1 Ultra-Rare": 79,
    "S1 Common": 155,
    "S2 Epic": 79,
    "S1 Epic": 25,
    "S1 Rare": 45,
    "S2 Common": 414,
    "S2 Rare": 67,
    "S1 Uncommon": 83,
    "S2 Legendary": 280,
    "S2 Uncommon": 60,
    "S2 Ultra-Rare": 15,
    "S3 Epic": 1754,
    "S3 Rare": 327,
    "S3 Uncommon": 470,
    "S3 Common": 374,
    "S3 Ultra-Rare": 310,
    "S3 Legendary": 217
  },
  {
    "Nation": "Tape",
    "Junk Value": 577.8,
    "Bank": 1778.51,
    "Deck Value": 28526.92,
    "Card Count": 5552,
    "Deck Capacity": 5135,
    "Epic": 309,
    "Legendary": 203,
    "Ultra-Rare": 733,
    "Common": 2970,
    "Rare": 457,
    "Uncommon": 880,
    "S1": 6,
    "S2": 378,
    "S3": 5168,
    "S1 Epic": 1,
    "S2 Epic": 106,
    "S1 Legendary": 5,
    "S2 Ultra-Rare": 52,
    "S2 Common": 156,
    "S2 Rare": 29,
    "S2 Legendary": 14,
    "S2 Uncommon": 21,
    "S3 Uncommon": 859,
    "S3 Common": 2814,
    "S3 Epic": 202,
    "S3 Ultra-Rare": 681,
    "S3 Rare": 428,
    "S3 Legendary": 184
  },
  {
    "Nation": "Grea Kriopia",
    "Junk Value": 369.49,
    "Bank": 269.95,
    "Deck Value": 27871.02,
    "Card Count": 948,
    "Deck Capacity": 2779,
    "Legendary": 305,
    "Ultra-Rare": 71,
    "Common": 379,
    "Rare": 37,
    "Epic": 86,
    "Uncommon": 70,
    "S1": 71,
    "S2": 822,
    "S3": 55,
    "S1 Legendary": 40,
    "S1 Ultra-Rare": 6,
    "S2 Common": 363,
    "S1 Rare": 2,
    "S1 Epic": 16,
    "S2 Ultra-Rare": 54,
    "S2 Epic": 60,
    "S1 Uncommon": 4,
    "S2 Legendary": 252,
    "S1 Common": 3,
    "S2 Uncommon": 62,
    "S2 Rare": 31,
    "S3 Legendary": 13,
    "S3 Ultra-Rare": 11,
    "S3 Rare": 4,
    "S3 Common": 13,
    "S3 Uncommon": 4,
    "S3 Epic": 10
  },
  {
    "Nation": "Alistia",
    "Junk Value": 482.21,
    "Bank": 114.24,
    "Deck Value": 27730.07,
    "Card Count": 3370,
    "Deck Capacity": 2005,
    "Common": 1486,
    "Ultra-Rare": 267,
    "Legendary": 302,
    "Uncommon": 859,
    "Epic": 138,
    "Rare": 318,
    "S1": 408,
    "S2": 475,
    "S3": 2487,
    "S1 Common": 192,
    "S1 Ultra-Rare": 26,
    "S1 Legendary": 90,
    "S1 Uncommon": 72,
    "S1 Epic": 14,
    "S2 Legendary": 179,
    "S1 Rare": 14,
    "S2 Epic": 16,
    "S2 Uncommon": 185,
    "S2 Rare": 17,
    "S2 Common": 53,
    "S2 Ultra-Rare": 25,
    "S3 Ultra-Rare": 216,
    "S3 Common": 1241,
    "S3 Rare": 287,
    "S3 Uncommon": 602,
    "S3 Epic": 108,
    "S3 Legendary": 33
  },
  {
    "Nation": "Von Zeischter",
    "Junk Value": 511.58,
    "Bank": 1823.67,
    "Deck Value": 26800.83,
    "Card Count": 2973,
    "Deck Capacity": 4392,
    "Common": 1473,
    "Uncommon": 655,
    "Legendary": 332,
    "Ultra-Rare": 153,
    "Rare": 157,
    "Epic": 203,
    "S1": 55,
    "S2": 330,
    "S3": 2588,
    "S1 Common": 21,
    "S1 Uncommon": 17,
    "S1 Legendary": 6,
    "S1 Ultra-Rare": 2,
    "S1 Rare": 8,
    "S2 Common": 154,
    "S2 Epic": 4,
    "S2 Legendary": 6,
    "S2 Rare": 15,
    "S2 Uncommon": 134,
    "S2 Ultra-Rare": 17,
    "S3 Uncommon": 504,
    "S3 Legendary": 320,
    "S3 Common": 1298,
    "S3 Epic": 198,
    "S3 Rare": 134,
    "S3 Ultra-Rare": 134,
    "S1 Epic": 1
  },
  {
    "Nation": "Farrakhan",
    "Junk Value": 278.88,
    "Bank": 13317.9,
    "Deck Value": 26509.05,
    "Card Count": 1073,
    "Deck Capacity": 5864,
    "Common": 433,
    "Uncommon": 97,
    "Epic": 539,
    "Ultra-Rare": 1,
    "Rare": 3,
    "S1": 517,
    "S2": 405,
    "S3": 151,
    "S1 Common": 317,
    "S1 Uncommon": 97,
    "S1 Epic": 103,
    "S2 Epic": 300,
    "S2 Common": 104,
    "S2 Ultra-Rare": 1,
    "S3 Rare": 3,
    "S3 Common": 12,
    "S3 Epic": 136
  },
  {
    "Nation": "Hendricksons",
    "Junk Value": 385.36,
    "Bank": 3424.42,
    "Deck Value": 26124.91,
    "Card Count": 516,
    "Deck Capacity": 1296,
    "Uncommon": 47,
    "Legendary": 375,
    "Common": 61,
    "Ultra-Rare": 17,
    "Epic": 8,
    "Rare": 8,
    "S1": 123,
    "S2": 84,
    "S3": 309,
    "S1 Uncommon": 36,
    "S1 Legendary": 42,
    "S1 Common": 40,
    "S2 Uncommon": 3,
    "S1 Ultra-Rare": 3,
    "S2 Legendary": 78,
    "S2 Epic": 1,
    "S2 Ultra-Rare": 2,
    "S3 Legendary": 255,
    "S3 Common": 21,
    "S3 Rare": 8,
    "S3 Uncommon": 8,
    "S3 Epic": 5,
    "S3 Ultra-Rare": 12,
    "S1 Epic": 2
  },
  {
    "Nation": "Radicalania",
    "Junk Value": 1776.51,
    "Bank": 468.31,
    "Deck Value": 25627.93,
    "Card Count": 8162,
    "Deck Capacity": 4287,
    "Common": 521,
    "Uncommon": 422,
    "Epic": 44,
    "Ultra-Rare": 6761,
    "Rare": 38,
    "Legendary": 376,
    "S2": 1188,
    "S1": 13,
    "S3": 6961,
    "S2 Common": 517,
    "S2 Uncommon": 405,
    "S2 Epic": 28,
    "S1 Uncommon": 12,
    "S2 Ultra-Rare": 40,
    "S2 Rare": 29,
    "S2 Legendary": 169,
    "S3 Ultra-Rare": 6721,
    "S3 Legendary": 207,
    "S3 Epic": 15,
    "S3 Rare": 9,
    "S3 Uncommon": 5,
    "S3 Common": 4,
    "S1 Epic": 1
  },
  {
    "Nation": "Rhenna",
    "Junk Value": 549.15,
    "Bank": 561.94,
    "Deck Value": 25355.32,
    "Card Count": 2137,
    "Deck Capacity": 1144,
    "Epic": 303,
    "Legendary": 347,
    "Common": 815,
    "Ultra-Rare": 97,
    "Uncommon": 462,
    "Rare": 113,
    "S1": 46,
    "S2": 60,
    "S3": 2031,
    "S1 Epic": 8,
    "S2 Epic": 12,
    "S2 Legendary": 4,
    "S2 Common": 20,
    "S2 Ultra-Rare": 6,
    "S2 Uncommon": 18,
    "S1 Uncommon": 7,
    "S1 Common": 26,
    "S3 Uncommon": 437,
    "S3 Legendary": 343,
    "S3 Common": 769,
    "S3 Epic": 283,
    "S1 Rare": 3,
    "S3 Rare": 110,
    "S3 Ultra-Rare": 89,
    "S1 Ultra-Rare": 2
  },
  {
    "Nation": "Timao",
    "Junk Value": 565.36,
    "Bank": 69.09,
    "Deck Value": 25101.96,
    "Card Count": 1469,
    "Deck Capacity": 2779,
    "Epic": 1083,
    "Uncommon": 124,
    "Ultra-Rare": 78,
    "Rare": 77,
    "Common": 106,
    "Legendary": 1,
    "S1": 123,
    "S2": 450,
    "S3": 896,
    "S1 Epic": 102,
    "S1 Uncommon": 9,
    "S1 Ultra-Rare": 5,
    "S2 Epic": 318,
    "S2 Rare": 37,
    "S2 Ultra-Rare": 19,
    "S2 Uncommon": 52,
    "S2 Common": 24,
    "S3 Epic": 663,
    "S3 Uncommon": 63,
    "S3 Rare": 37,
    "S3 Ultra-Rare": 54,
    "S1 Common": 4,
    "S3 Common": 78,
    "S1 Rare": 3,
    "S3 Legendary": 1
  },
  {
    "Nation": "Rain Delay",
    "Junk Value": 1295.21,
    "Bank": 610.78,
    "Deck Value": 25089.63,
    "Card Count": 13879,
    "Deck Capacity": 7083,
    "Rare": 1393,
    "Common": 5661,
    "Uncommon": 3778,
    "Epic": 1129,
    "Ultra-Rare": 1791,
    "Legendary": 127,
    "S1": 3859,
    "S2": 3420,
    "S3": 6600,
    "S1 Rare": 316,
    "S1 Common": 1387,
    "S1 Uncommon": 1157,
    "S1 Epic": 420,
    "S1 Ultra-Rare": 502,
    "S2 Common": 1455,
    "S1 Legendary": 77,
    "S2 Uncommon": 833,
    "S2 Ultra-Rare": 537,
    "S2 Rare": 285,
    "S2 Epic": 281,
    "S2 Legendary": 29,
    "S3 Common": 2819,
    "S3 Uncommon": 1788,
    "S3 Epic": 428,
    "S3 Rare": 792,
    "S3 Ultra-Rare": 752,
    "S3 Legendary": 21
  },
  {
    "Nation": "Sea Dolphin Lovers",
    "Junk Value": 801.89,
    "Bank": 105.69,
    "Deck Value": 25067.11,
    "Card Count": 2236,
    "Deck Capacity": 3606,
    "Legendary": 341,
    "Common": 434,
    "Uncommon": 323,
    "Ultra-Rare": 202,
    "Epic": 800,
    "Rare": 136,
    "S1": 611,
    "S2": 662,
    "S3": 963,
    "S1 Legendary": 95,
    "S1 Common": 181,
    "S1 Uncommon": 84,
    "S1 Ultra-Rare": 82,
    "S1 Epic": 112,
    "S2 Legendary": 191,
    "S1 Rare": 57,
    "S2 Epic": 150,
    "S2 Ultra-Rare": 57,
    "S2 Common": 118,
    "S2 Uncommon": 122,
    "S2 Rare": 24,
    "S3 Uncommon": 117,
    "S3 Ultra-Rare": 63,
    "S3 Legendary": 55,
    "S3 Epic": 538,
    "S3 Common": 135,
    "S3 Rare": 55
  },
  {
    "Nation": "Oofery",
    "Junk Value": 206.26,
    "Bank": 609.63,
    "Deck Value": 23659.37,
    "Card Count": 691,
    "Deck Capacity": 4931,
    "Common": 246,
    "Uncommon": 78,
    "Ultra-Rare": 137,
    "Rare": 33,
    "Legendary": 148,
    "Epic": 49,
    "S2": 534,
    "S1": 73,
    "S3": 84,
    "S2 Common": 233,
    "S1 Uncommon": 6,
    "S2 Ultra-Rare": 50,
    "S1 Ultra-Rare": 5,
    "S1 Rare": 5,
    "S1 Legendary": 40,
    "S1 Common": 13,
    "S2 Epic": 45,
    "S2 Uncommon": 72,
    "S2 Legendary": 107,
    "S2 Rare": 27,
    "S1 Epic": 4,
    "S3 Ultra-Rare": 82,
    "S3 Rare": 1,
    "S3 Legendary": 1
  },
  {
    "Nation": "The Cat And Mouse Game",
    "Junk Value": 347,
    "Bank": 8195.98,
    "Deck Value": 22147.33,
    "Card Count": 836,
    "Deck Capacity": 1296,
    "Common": 295,
    "Uncommon": 117,
    "Legendary": 294,
    "Epic": 76,
    "Ultra-Rare": 31,
    "Rare": 23,
    "S2": 199,
    "S1": 62,
    "S3": 575,
    "S2 Common": 16,
    "S2 Uncommon": 82,
    "S2 Legendary": 73,
    "S1 Legendary": 8,
    "S2 Epic": 24,
    "S1 Uncommon": 9,
    "S2 Ultra-Rare": 2,
    "S1 Ultra-Rare": 2,
    "S1 Common": 36,
    "S2 Rare": 2,
    "S1 Epic": 2,
    "S3 Common": 243,
    "S3 Legendary": 213,
    "S1 Rare": 5,
    "S3 Uncommon": 26,
    "S3 Epic": 50,
    "S3 Ultra-Rare": 27,
    "S3 Rare": 16
  },
  {
    "Nation": "Pinky Queen",
    "Junk Value": 505.47,
    "Bank": 402.56,
    "Deck Value": 21928.69,
    "Card Count": 3684,
    "Deck Capacity": 3606,
    "Epic": 372,
    "Rare": 337,
    "Ultra-Rare": 321,
    "Legendary": 203,
    "Common": 1757,
    "Uncommon": 694,
    "S1": 422,
    "S2": 997,
    "S3": 2265,
    "S1 Epic": 81,
    "S1 Rare": 45,
    "S1 Ultra-Rare": 33,
    "S1 Legendary": 51,
    "S1 Common": 160,
    "S1 Uncommon": 52,
    "S2 Common": 384,
    "S2 Epic": 115,
    "S2 Legendary": 106,
    "S2 Uncommon": 234,
    "S2 Ultra-Rare": 64,
    "S2 Rare": 94,
    "S3 Common": 1213,
    "S3 Ultra-Rare": 224,
    "S3 Uncommon": 408,
    "S3 Epic": 176,
    "S3 Legendary": 46,
    "S3 Rare": 198
  },
  {
    "Nation": "Nationstates Nation State",
    "Junk Value": 375.17,
    "Bank": 622.52,
    "Deck Value": 21844.04,
    "Card Count": 2824,
    "Deck Capacity": 3000,
    "Common": 2372,
    "Legendary": 325,
    "Epic": 39,
    "Rare": 48,
    "Ultra-Rare": 33,
    "Uncommon": 7,
    "S2": 51,
    "S3": 2772,
    "S1": 1,
    "S2 Common": 51,
    "S3 Common": 2321,
    "S3 Legendary": 325,
    "S3 Epic": 39,
    "S3 Rare": 48,
    "S3 Ultra-Rare": 33,
    "S1 Uncommon": 1,
    "S3 Uncommon": 6
  },
  {
    "Nation": "Mediobogdum",
    "Junk Value": 392.4,
    "Bank": 1173.89,
    "Deck Value": 21546.69,
    "Card Count": 526,
    "Deck Capacity": 2005,
    "Epic": 4,
    "Legendary": 387,
    "Common": 90,
    "Uncommon": 26,
    "Rare": 13,
    "Ultra-Rare": 6,
    "S1": 2,
    "S2": 276,
    "S3": 248,
    "S1 Epic": 1,
    "S2 Legendary": 169,
    "S2 Common": 76,
    "S2 Uncommon": 18,
    "S2 Rare": 7,
    "S2 Ultra-Rare": 4,
    "S2 Epic": 2,
    "S1 Common": 1,
    "S3 Legendary": 218,
    "S3 Ultra-Rare": 2,
    "S3 Uncommon": 8,
    "S3 Common": 13,
    "S3 Rare": 6,
    "S3 Epic": 1
  },
  {
    "Nation": "Anjan Kloss",
    "Junk Value": 1002.23,
    "Bank": 943.93,
    "Deck Value": 21347.92,
    "Card Count": 1933,
    "Deck Capacity": 2000,
    "Legendary": 322,
    "Epic": 1340,
    "Common": 98,
    "Ultra-Rare": 10,
    "Uncommon": 145,
    "Rare": 18,
    "S1": 19,
    "S2": 31,
    "S3": 1883,
    "S1 Legendary": 1,
    "S2 Epic": 21,
    "S3 Legendary": 321,
    "S3 Common": 91,
    "S3 Epic": 1306,
    "S3 Ultra-Rare": 10,
    "S3 Uncommon": 137,
    "S1 Epic": 13,
    "S2 Uncommon": 6,
    "S3 Rare": 18,
    "S1 Uncommon": 2,
    "S1 Common": 3,
    "S2 Common": 4
  },
  {
    "Nation": "Eugeniee",
    "Junk Value": 585.88,
    "Bank": 1885.35,
    "Deck Value": 20972.16,
    "Card Count": 3381,
    "Deck Capacity": 3418,
    "Common": 1288,
    "Ultra-Rare": 474,
    "Epic": 531,
    "Uncommon": 454,
    "Legendary": 190,
    "Rare": 444,
    "S1": 215,
    "S2": 317,
    "S3": 2849,
    "S1 Common": 94,
    "S1 Ultra-Rare": 22,
    "S1 Epic": 57,
    "S1 Uncommon": 33,
    "S2 Common": 106,
    "S1 Legendary": 7,
    "S2 Epic": 40,
    "S2 Uncommon": 22,
    "S2 Rare": 33,
    "S2 Ultra-Rare": 26,
    "S2 Legendary": 90,
    "S3 Ultra-Rare": 426,
    "S3 Rare": 409,
    "S3 Common": 1088,
    "S3 Uncommon": 399,
    "S3 Legendary": 93,
    "S3 Epic": 434,
    "S1 Rare": 2
  },
  {
    "Nation": "Sunhizria",
    "Junk Value": 288.3,
    "Bank": 147.45,
    "Deck Value": 20854.11,
    "Card Count": 422,
    "Deck Capacity": 1642,
    "Legendary": 184,
    "Epic": 192,
    "Ultra-Rare": 40,
    "Uncommon": 6,
    "S1": 196,
    "S2": 76,
    "S3": 150,
    "S1 Legendary": 184,
    "S1 Epic": 9,
    "S1 Ultra-Rare": 3,
    "S2 Ultra-Rare": 27,
    "S2 Epic": 43,
    "S2 Uncommon": 6,
    "S3 Ultra-Rare": 10,
    "S3 Epic": 140
  },
  {
    "Nation": "Mind The Gap",
    "Junk Value": 84.92,
    "Bank": 0,
    "Deck Value": 20788.5,
    "Card Count": 1000,
    "Deck Capacity": 1000,
    "Rare": 73,
    "Epic": 69,
    "Ultra-Rare": 84,
    "Uncommon": 647,
    "Common": 127,
    "S2": 1000,
    "S2 Rare": 73,
    "S2 Epic": 69,
    "S2 Ultra-Rare": 84,
    "S2 Uncommon": 647,
    "S2 Common": 127
  },
  {
    "Nation": "Ethnon",
    "Junk Value": 462.07,
    "Bank": 512.01,
    "Deck Value": 20527.63,
    "Card Count": 1839,
    "Deck Capacity": 5864,
    "Legendary": 233,
    "Ultra-Rare": 273,
    "Common": 532,
    "Uncommon": 213,
    "Epic": 317,
    "Rare": 271,
    "S1": 719,
    "S2": 770,
    "S3": 350,
    "S1 Legendary": 124,
    "S1 Ultra-Rare": 128,
    "S1 Common": 123,
    "S1 Uncommon": 117,
    "S2 Common": 195,
    "S2 Epic": 216,
    "S1 Rare": 144,
    "S2 Rare": 114,
    "S1 Epic": 83,
    "S2 Ultra-Rare": 127,
    "S2 Uncommon": 47,
    "S2 Legendary": 71,
    "S3 Common": 214,
    "S3 Legendary": 38,
    "S3 Epic": 18,
    "S3 Uncommon": 49,
    "S3 Rare": 13,
    "S3 Ultra-Rare": 18
  },
  {
    "Nation": "Arlizplot",
    "Junk Value": 332.58,
    "Bank": 277.98,
    "Deck Value": 20179.51,
    "Card Count": 2902,
    "Deck Capacity": 1720,
    "Common": 1883,
    "Ultra-Rare": 81,
    "Uncommon": 521,
    "Rare": 92,
    "Epic": 107,
    "Legendary": 218,
    "S1": 717,
    "S2": 192,
    "S3": 1993,
    "S1 Common": 575,
    "S1 Ultra-Rare": 14,
    "S1 Uncommon": 99,
    "S1 Rare": 18,
    "S1 Epic": 9,
    "S2 Common": 125,
    "S2 Epic": 24,
    "S2 Ultra-Rare": 13,
    "S2 Legendary": 17,
    "S2 Uncommon": 11,
    "S2 Rare": 2,
    "S3 Common": 1183,
    "S3 Rare": 72,
    "S3 Ultra-Rare": 54,
    "S3 Legendary": 199,
    "S3 Epic": 74,
    "S3 Uncommon": 411,
    "S1 Legendary": 2
  },
  {
    "Nation": "Altivia",
    "Junk Value": 358.63,
    "Bank": 241.7,
    "Deck Value": 19987.78,
    "Card Count": 1326,
    "Deck Capacity": 2779,
    "Common": 263,
    "Legendary": 197,
    "Uncommon": 482,
    "Rare": 113,
    "Epic": 269,
    "Ultra-Rare": 2,
    "S1": 17,
    "S2": 844,
    "S3": 465,
    "S1 Common": 5,
    "S1 Legendary": 9,
    "S2 Legendary": 82,
    "S2 Uncommon": 482,
    "S2 Rare": 108,
    "S2 Common": 172,
    "S3 Common": 86,
    "S3 Epic": 269,
    "S3 Legendary": 106,
    "S3 Rare": 2,
    "S3 Ultra-Rare": 2,
    "S1 Rare": 3
  },
  {
    "Nation": "Richardian Savoy",
    "Junk Value": 734.58,
    "Bank": 1651.34,
    "Deck Value": 19843.32,
    "Card Count": 2848,
    "Deck Capacity": 2005,
    "Uncommon": 447,
    "Common": 923,
    "Legendary": 286,
    "Rare": 223,
    "Ultra-Rare": 225,
    "Epic": 744,
    "S1": 62,
    "S2": 1009,
    "S3": 1777,
    "S1 Uncommon": 14,
    "S2 Common": 426,
    "S2 Legendary": 17,
    "S2 Uncommon": 283,
    "S2 Rare": 119,
    "S2 Ultra-Rare": 77,
    "S2 Epic": 87,
    "S1 Common": 26,
    "S1 Epic": 12,
    "S1 Rare": 7,
    "S1 Ultra-Rare": 3,
    "S3 Uncommon": 150,
    "S3 Common": 471,
    "S3 Epic": 645,
    "S3 Rare": 97,
    "S3 Ultra-Rare": 145,
    "S3 Legendary": 269
  },
  {
    "Nation": "Hyperwolf",
    "Junk Value": 309.09,
    "Bank": 525.07,
    "Deck Value": 19638.96,
    "Card Count": 1417,
    "Deck Capacity": 918,
    "Ultra-Rare": 107,
    "Epic": 40,
    "Common": 484,
    "Rare": 146,
    "Legendary": 243,
    "Uncommon": 397,
    "S2": 106,
    "S1": 94,
    "S3": 1217,
    "S2 Ultra-Rare": 34,
    "S2 Epic": 6,
    "S1 Common": 72,
    "S2 Rare": 10,
    "S2 Legendary": 8,
    "S1 Uncommon": 14,
    "S2 Common": 29,
    "S2 Uncommon": 19,
    "S3 Common": 383,
    "S3 Uncommon": 364,
    "S3 Rare": 131,
    "S3 Legendary": 235,
    "S3 Ultra-Rare": 71,
    "S3 Epic": 33,
    "S1 Rare": 5,
    "S1 Ultra-Rare": 2,
    "S1 Epic": 1
  },
  {
    "Nation": "Refiria",
    "Junk Value": 322.84,
    "Bank": 271.62,
    "Deck Value": 19546.14,
    "Card Count": 1290,
    "Deck Capacity": 2005,
    "Legendary": 265,
    "Common": 479,
    "Uncommon": 419,
    "Epic": 53,
    "Ultra-Rare": 28,
    "Rare": 46,
    "S2": 390,
    "S1": 62,
    "S3": 838,
    "S2 Legendary": 123,
    "S2 Common": 182,
    "S1 Uncommon": 9,
    "S1 Legendary": 20,
    "S1 Epic": 9,
    "S1 Ultra-Rare": 2,
    "S1 Common": 16,
    "S2 Uncommon": 50,
    "S2 Ultra-Rare": 11,
    "S2 Epic": 13,
    "S2 Rare": 11,
    "S1 Rare": 6,
    "S3 Uncommon": 360,
    "S3 Common": 281,
    "S3 Legendary": 122,
    "S3 Rare": 29,
    "S3 Epic": 31,
    "S3 Ultra-Rare": 15
  },
  {
    "Nation": "Pumpty Dumpty",
    "Junk Value": 95.08,
    "Bank": 9612.69,
    "Deck Value": 19234.74,
    "Card Count": 426,
    "Deck Capacity": 3606,
    "Legendary": 90,
    "Common": 293,
    "Uncommon": 43,
    "S1": 6,
    "S2": 405,
    "S3": 15,
    "S1 Legendary": 4,
    "S2 Common": 278,
    "S2 Legendary": 84,
    "S1 Common": 2,
    "S2 Uncommon": 43,
    "S3 Common": 13,
    "S3 Legendary": 2
  },
  {
    "Nation": "Economichunger",
    "Junk Value": 350.5,
    "Bank": 632.89,
    "Deck Value": 18976.09,
    "Card Count": 967,
    "Deck Capacity": 5864,
    "Legendary": 281,
    "Rare": 50,
    "Common": 340,
    "Uncommon": 156,
    "Epic": 101,
    "Ultra-Rare": 39,
    "S1": 177,
    "S2": 678,
    "S3": 112,
    "S1 Legendary": 24,
    "S1 Rare": 9,
    "S1 Common": 74,
    "S1 Uncommon": 40,
    "S1 Epic": 15,
    "S1 Ultra-Rare": 15,
    "S2 Uncommon": 96,
    "S2 Common": 237,
    "S2 Legendary": 230,
    "S2 Epic": 66,
    "S2 Rare": 32,
    "S2 Ultra-Rare": 17,
    "S3 Uncommon": 20,
    "S3 Legendary": 27,
    "S3 Common": 29,
    "S3 Rare": 9,
    "S3 Epic": 20,
    "S3 Ultra-Rare": 7
  }
]